lameg/__init__.py
lameg/invert.py
lameg/laminar.py
lameg/postinstall.py
lameg/simulate.py
lameg/surf.py
lameg/util.py
lameg/viz.py
lameg/assets/erc_logo.jpg
lameg/assets/fpa_logo.png
lameg/assets/logo.png
lameg/assets/big_brain_layer_thickness/tpl-bigbrain_hemi-L_desc-layer1_thickness.shape.gii
lameg/assets/big_brain_layer_thickness/tpl-bigbrain_hemi-L_desc-layer2_thickness.shape.gii
lameg/assets/big_brain_layer_thickness/tpl-bigbrain_hemi-L_desc-layer3_thickness.shape.gii
lameg/assets/big_brain_layer_thickness/tpl-bigbrain_hemi-L_desc-layer4_thickness.shape.gii
lameg/assets/big_brain_layer_thickness/tpl-bigbrain_hemi-L_desc-layer5_thickness.shape.gii
lameg/assets/big_brain_layer_thickness/tpl-bigbrain_hemi-L_desc-layer6_thickness.shape.gii
lameg/assets/big_brain_layer_thickness/tpl-bigbrain_hemi-R_desc-layer1_thickness.shape.gii
lameg/assets/big_brain_layer_thickness/tpl-bigbrain_hemi-R_desc-layer2_thickness.shape.gii
lameg/assets/big_brain_layer_thickness/tpl-bigbrain_hemi-R_desc-layer3_thickness.shape.gii
lameg/assets/big_brain_layer_thickness/tpl-bigbrain_hemi-R_desc-layer4_thickness.shape.gii
lameg/assets/big_brain_layer_thickness/tpl-bigbrain_hemi-R_desc-layer5_thickness.shape.gii
lameg/assets/big_brain_layer_thickness/tpl-bigbrain_hemi-R_desc-layer6_thickness.shape.gii
lameg/assets/big_brain_layer_thickness/tpl-fsaverage_hemi-L_den-164k_desc-layer1_thickness.shape.gii
lameg/assets/big_brain_layer_thickness/tpl-fsaverage_hemi-L_den-164k_desc-layer2_thickness.shape.gii
lameg/assets/big_brain_layer_thickness/tpl-fsaverage_hemi-L_den-164k_desc-layer3_thickness.shape.gii
lameg/assets/big_brain_layer_thickness/tpl-fsaverage_hemi-L_den-164k_desc-layer4_thickness.shape.gii
lameg/assets/big_brain_layer_thickness/tpl-fsaverage_hemi-L_den-164k_desc-layer5_thickness.shape.gii
lameg/assets/big_brain_layer_thickness/tpl-fsaverage_hemi-L_den-164k_desc-layer6_thickness.shape.gii
lameg-0.1.3.dist-info/LICENSE
lameg-0.1.3.dist-info/METADATA
lameg-0.1.3.dist-info/WHEEL
lameg-0.1.3.dist-info/entry_points.txt
lameg-0.1.3.dist-info/top_level.txt
lameg-0.1.3.dist-info/RECORD
