Metadata-Version: 2.1
Name: lameg
Version: 0.1.3
Summary: A toolbox for laminar inference with MEG
Home-page: https://github.com/danclab/laMEG
Author: DANC lab
Author-email: James Bonaiuto <james.bonaiuto@isc.cnrs.fr>, DANC lab <danclab.info@gmail.com>
Project-URL: homepage, https://github.com/danclab/laMEG
Classifier: Intended Audience :: Science/Research
Classifier: Intended Audience :: Developers
Classifier: License :: OSI Approved
Classifier: Programming Language :: Python
Classifier: Topic :: Software Development
Classifier: Topic :: Scientific/Engineering
Classifier: Operating System :: Unix
Requires-Python: ~=3.7
License-File: LICENSE
Requires-Dist: nibabel (==3.2.2)
Requires-Dist: vtk (==9.3.0)
Requires-Dist: numpy (==1.21.6)
Requires-Dist: scipy (==1.5.4)
Requires-Dist: matplotlib (==3.3.4)
Requires-Dist: joblib (==1.1.1)
Requires-Dist: setuptools (==59.6.0)
Requires-Dist: elephant (==0.10.0)
Requires-Dist: neo (==0.9.0)
Requires-Dist: quantities (==0.13.0)
Requires-Dist: h5py (==3.1.0)
Requires-Dist: mne (==1.3.1)
Requires-Dist: notebook (==6.4.10)
Requires-Dist: widgetsnbextension (==3.6.6)
Requires-Dist: ipywidgets (==7.8.1)
Requires-Dist: jupyterlab-widgets (==1.1.7)
Requires-Dist: k3d (==2.14.5)
